ivendi/__init__.py
ivendi/prefecttools.py
ivprefecttools-0.0.15.dist-info/METADATA
ivprefecttools-0.0.15.dist-info/WHEEL
ivprefecttools-0.0.15.dist-info/top_level.txt
ivprefecttools-0.0.15.dist-info/RECORD
