Metadata-Version: 2.1
Name: ivprefecttools
Version: 0.0.15
Summary: package for reusable functionality across flows
Author: stevef
Author-email: 
Classifier: Programming Language :: Python :: 3
Classifier: License :: OSI Approved :: MIT License
Classifier: Operating System :: OS Independent
Requires-Python: >=3.9
Requires-Dist: r7insight-python
